gitignoreformatter.py
gitignoreformatter-1.1.3.0.dist-info/LICENSE
gitignoreformatter-1.1.3.0.dist-info/METADATA
gitignoreformatter-1.1.3.0.dist-info/WHEEL
gitignoreformatter-1.1.3.0.dist-info/entry_points.txt
gitignoreformatter-1.1.3.0.dist-info/top_level.txt
gitignoreformatter-1.1.3.0.dist-info/zip-safe
gitignoreformatter-1.1.3.0.dist-info/RECORD
