Metadata-Version: 2.1
Name: gitignoreformatter
Version: 1.1.3.0
Summary: A basic CLI program that allows for quick formatting of a .gitignore file
Author-email: Markus Hammer <107761433+MarkusHammer@users.noreply.github.com>
License: Mozilla Public License Version 2.0
Project-URL: Homepage, https://github.com/MarkusHammer/gitignore-formatter
Project-URL: Github, https://github.com/MarkusHammer/gitignore-formatter
Project-URL: Issues, https://github.com/MarkusHammer/gitignore-formatter/issues
Project-URL: Pull Requests, https://github.com/MarkusHammer/gitignore-formatter/pulls
Project-URL: Git, https://github.com/MarkusHammer/gitignore-formatter.git
Keywords: git,gitignore,.gitignore,ignore,formatter,tool,devtool,small,simple,development,utility
Classifier: License :: OSI Approved :: Mozilla Public License 2.0 (MPL 2.0)
Classifier: Development Status :: 5 - Production/Stable
Classifier: Environment :: Console
Classifier: Intended Audience :: Developers
Classifier: Natural Language :: English
Classifier: Topic :: Software Development :: Version Control
Classifier: Topic :: Software Development :: Version Control :: Git
Classifier: Topic :: Utilities
Classifier: Programming Language :: Python
Classifier: Programming Language :: Python :: 3
Requires-Python: >=3.0
License-File: LICENSE
Requires-Dist: argparse
Provides-Extra: cli
Requires-Dist: pathlib ; extra == 'cli'
Provides-Extra: dev
Requires-Dist: setuptools (>=64.0.0) ; extra == 'dev'
Requires-Dist: pip-tools ; extra == 'dev'
Requires-Dist: validate-pyproject[all] ; extra == 'dev'
Requires-Dist: build ; extra == 'dev'
Requires-Dist: twine ; extra == 'dev'
